hyponcloud/__init__.py
hyponcloud/_version.py
hyponcloud/client.py
hyponcloud/exceptions.py
hyponcloud/models.py
hyponcloud/py.typed
hyponcloud-0.2.2.dist-info/licenses/LICENSE
hyponcloud-0.2.2.dist-info/METADATA
hyponcloud-0.2.2.dist-info/WHEEL
hyponcloud-0.2.2.dist-info/top_level.txt
hyponcloud-0.2.2.dist-info/RECORD
