Metadata-Version: 2.4
Name: hyponcloud
Version: 0.2.2
Summary: Python library for Hypontech Cloud API
Author-email: jcisio <hainam@jcisio.com>
License: MIT
Project-URL: Homepage, https://github.com/jcisio/hyponcloud
Project-URL: Repository, https://github.com/jcisio/hyponcloud
Project-URL: Issues, https://github.com/jcisio/hyponcloud/issues
Keywords: hypontech,solar,inverter,api,async
Classifier: Development Status :: 4 - Beta
Classifier: Intended Audience :: Developers
Classifier: License :: OSI Approved :: MIT License
Classifier: Operating System :: OS Independent
Classifier: Programming Language :: Python :: 3
Classifier: Programming Language :: Python :: 3.11
Classifier: Programming Language :: Python :: 3.12
Classifier: Programming Language :: Python :: 3.13
Classifier: Topic :: Home Automation
Classifier: Topic :: Software Development :: Libraries :: Python Modules
Requires-Python: >=3.11
License-File: LICENSE
Requires-Dist: aiohttp>=3.8.0
Requires-Dist: mashumaro>=3.11
Provides-Extra: dev
Requires-Dist: pytest>=7.0.0; extra == "dev"
Requires-Dist: pytest-asyncio>=0.21.0; extra == "dev"
Requires-Dist: pytest-cov>=4.0.0; extra == "dev"
Requires-Dist: ruff>=0.1.0; extra == "dev"
Requires-Dist: mypy>=1.0.0; extra == "dev"
Requires-Dist: pre-commit>=3.0.0; extra == "dev"
Dynamic: license-file
